[
  {
    "destination": "boedele",
    "date": "d20140927",
    "type": "hike",
    "track": true,
    "detailMap": "austria",
    "shortTitle": "Bödele",
    "title": "Bödele - Fohramoos",
    "movie": "9tqSmvoeL9s",
    "intro": "Erst Mittags ging es am letzten Samstag los zu einem Spaziergang auf dem Bödele, dem Hausberg Dornbirns oberhalb des Rheintals.<br />\nBei schönstem und warmem Herbstwetter Ankunft auf den großen Parkplätzen entlang der Passstraße des Bödeles.",
    "landmarks": [
      {
        "photos": [
          {
            "name": "002",
            "date": "2014-09-27T13:27:45.000+02:00",
            "width": 1776,
            "height": 1080
          }
        ],
        "videos": [],
        "text": "Zuerst ging es auf eine Runde durch das Fohramoos, einem großen Moor unter Naturschutz mit Wald und einzelnen Wiesen. Zuerst ging es um einen (aufgestauten) Moorsee mit tiefschwarzem Wasser und tollen Spiegelungen."
      },
      {
        "photos": [
          {
            "name": "004",
            "date": "2014-09-27T14:03:29.000+02:00",
            "width": 1620,
            "height": 1080
          },
          {
            "name": "006",
            "date": "2014-09-27T14:05:00.000+02:00",
            "width": 1620,
            "height": 1080
          }
        ],
        "videos": [],
        "text": "Nach einer etwas langweiligen Strecke auf einem Feldweg erreicht man die erste Moorwiese. Bei jedem Schritt wackelte der Boden. Das schöne Wetter und die herbstlichen Farben waren sehr fotogen. Leider sind überall in dem Gebiet Ferienhäuser verstreut, so dass man mit dem Blickwinkel etwas tricksen muss."
      },
      {
        "photos": [
          {
            "name": "009",
            "date": "2014-09-27T14:11:09.000+02:00",
            "width": 720,
            "height": 1080
          },
          {
            "name": "011",
            "date": "2014-09-27T14:12:37.000+02:00",
            "width": 1620,
            "height": 1080
          }
        ],
        "videos": [],
        "text": "Anschließend geht es über viele Holzstege weiter durch die moorigen Wälder und Wiesen."
      },
      {
        "photos": [
          {
            "name": "012",
            "date": "2014-09-27T14:12:45.000+02:00",
            "width": 1701,
            "height": 1080
          },
          {
            "name": "013",
            "date": "2014-09-27T14:13:01.000+02:00",
            "width": 720,
            "height": 1080
          },
          {
            "name": "014",
            "date": "2014-09-27T14:13:45.000+02:00",
            "width": 1620,
            "height": 1080
          }
        ],
        "videos": [],
        "text": "Die hochgewachsenen Gräser leuchteten rot im Sonnenlicht."
      },
      {
        "photos": [
          {
            "name": "015",
            "date": "2014-09-27T14:14:56.000+02:00",
            "width": 720,
            "height": 1080
          },
          {
            "name": "016",
            "date": "2014-09-27T14:15:50.000+02:00",
            "width": 1620,
            "height": 1080
          }
        ],
        "videos": [],
        "text": "Die Wälder dagegen überzogen von einem dichten Gewirr aus Wurzeln und weichem Moos."
      },
      {
        "photos": [
          {
            "name": "018",
            "date": "2014-09-27T14:28:55.000+02:00",
            "width": 1920,
            "height": 1074
          }
        ],
        "videos": [],
        "text": "Und natürlich viel Wasser."
      },
      {
        "photos": [
          {
            "name": "021",
            "date": "2014-09-27T14:53:29.000+02:00",
            "width": 1920,
            "height": 772
          }
        ],
        "videos": [],
        "text": "Nach dem Moor geht es entlang des Skigebiets und durch weitere Ferienhäuser zurück zur Straße.<br />\nDort dann eine gemütliche Mittagspause auf der Terrasse des Berghof Fetz."
      },
      {
        "photos": [
          {
            "name": "023",
            "date": "2014-09-27T16:20:31.000+02:00",
            "width": 1620,
            "height": 1080
          }
        ],
        "videos": [],
        "text": "Nach der Pause ging es dann zu einer weiteren Runde auf der anderen Seite der Straße. Zuerst ging es auf schmalem Steg durch ein weiteres Moor über den eigentlichen (etwas tiefer liegendem) Pass."
      },
      {
        "photos": [
          {
            "name": "025",
            "date": "2014-09-27T16:54:16.000+02:00",
            "width": 1620,
            "height": 1080
          }
        ],
        "videos": [],
        "text": "Und danach hoch auf einer kleinen Straße und das letzte Stück über eine Weide auf den kleinen Gipfel des Geißkopf. Aussicht gibts dort leider nur Richtung Bregenzerwald (die kleine Spitze ist z.B. die Mittagsspitze von Damüls). Der Blick zum Bodensee ist versperrt durch viele Tannen."
      },
      {
        "photos": [
          {
            "name": "026",
            "date": "2014-09-27T16:54:49.000+02:00",
            "width": 1920,
            "height": 888
          }
        ],
        "videos": [],
        "text": "Anschließend in der Abendsonne wieder ähnlich zurück zum Bödele (die Häuser im Hintergrund)."
      },
      {
        "photos": [
          {
            "name": "track1"
          }
        ],
        "videos": [],
        "text": "Gelaufene Strecke. Zweimal 4km mit nur kleinem Höhenunterschied und einfach zu gehenden Wegen."
      }
    ],
    "outro": "Fazit: Schöner Herbstspaziergang"
  }
]
